apigpio/__init__.py
apigpio/apigpio.py
apigpio/ctes.py
apigpio/utils.py
apigpio_mpf-0.0.4.dist-info/LICENSE.txt
apigpio_mpf-0.0.4.dist-info/METADATA
apigpio_mpf-0.0.4.dist-info/WHEEL
apigpio_mpf-0.0.4.dist-info/top_level.txt
apigpio_mpf-0.0.4.dist-info/RECORD
