Metadata-Version: 2.1
Name: apigpio-mpf
Version: 0.0.4
Summary: asyncio-based python client for pigpiod
Home-page: https://github.com/missionpinball/apigpio
Author: Pierre Rust
Author-email: pierre.rust@gmail.com
License: UNKNOWN
Keywords: gpio,pigpio,asyncio,raspberry
Platform: UNKNOWN
Classifier: Development Status :: 3 - Alpha
Classifier: Intended Audience :: Developers
Classifier: License :: OSI Approved :: MIT License
Classifier: Operating System :: OS Independent
Classifier: Programming Language :: Python :: 3.5
Classifier: Programming Language :: Python :: 3.6
Classifier: Programming Language :: Python :: 3.7
Classifier: Topic :: System :: Hardware :: Hardware Drivers
Classifier: Topic :: Software Development :: Libraries :: Python Modules
